{
  "manifestVersion": 1,
  "id": "vsts-heroku-cli",
  "name": "Heroku Tools",
  "description": "Heroku CLI Tools for VSTS.",
  "version": "1.0.5",
  "publisher": "seansobey",
  "icons": {
    "default": "vss-extension-icon.png"
  },
  "tags": [
    "Heroku"
  ],
  "links": {
    "home": {
      "uri": "https://github.com/SeanSobey/vsts-heroku-cli"
    },
    "getstarted": {
      "uri": "https://marketplace.visualstudio.com/items?itemName=seansobey.vsts-heroku-cli"
    },
    "issues": {
      "uri": "https://github.com/SeanSobey/vsts-heroku-cli/issues"
    },
    "license": {
      "uri": "https://github.com/SeanSobey/vsts-heroku-cli/blob/master/LICENSE"
    },
    "repository": {
      "uri": "https://github.com/SeanSobey/vsts-heroku-cli"
    },
    "learn": {
      "uri": "https://github.com/SeanSobey/vsts-heroku-cli/wiki"
    },
    "support": {
      "uri": "https://github.com/SeanSobey/vsts-heroku-cli/issues"
    }
  },
  "repository": {
    "type": "git",
    "uri": "https://github.com/SeanSobey/vsts-heroku-cli"
  },
  "screenshots": [],
  "branding": {
    "color": "rgb(167, 138, 201)",
    "theme": "light"
  },
  "galleryFlags": [],
  "scopes": [
    "vso.build",
    "vso.build_execute",
    "vso.release"
  ],
  "targets": [
    {
      "id": "Microsoft.VisualStudio.Services"
    }
  ],
  "categories": [
    "Build and release"
  ],
  "files": [
    {
      "path": "tasks/installCli"
    },
    {
      "path": "tasks/runCli"
    }
  ],
  "contributions": [
    {
      "id": "vsts-heroku-cli-install",
      "description": "Finds or Downloads and caches Heroku CLI and adds it to the PATH.",
      "type": "ms.vss-distributed-task.task",
      "targets": [
        "ms.vss-distributed-task.tasks"
      ],
      "properties": {
        "name": "tasks/installCli"
      }
    },
    {
      "id": "vsts-heroku-cli-run",
      "description": "Run a Heroku CLI command as a task.",
      "type": "ms.vss-distributed-task.task",
      "targets": [
        "ms.vss-distributed-task.tasks"
      ],
      "properties": {
        "name": "tasks/runCli"
      }
    }
  ]
}